{
    "AX": {
        "error": 0.0065975801085749915,
        "error_type": "SEM",
        "filter_outliers_dict": {
            "filter_outliers": true,
            "iterations": 1,
            "std_devs": 3,
            "use_iqr_filtering": false,
            "use_standard_deviation_filtering": false
        },
        "fit": "average",
        "fn": 60,
        "include_baseline_error": false,
        "n": 60,
        "outlier_excluded": [],
        "reviewed": true,
        "user_excluded": [],
        "value": 0.14836210291832685
    },
    "H1": {
        "error": 0.008095986066545702,
        "error_type": "SEM",
        "filter_outliers_dict": {
            "filter_outliers": true,
            "iterations": 1,
            "std_devs": 3,
            "use_iqr_filtering": false,
            "use_standard_deviation_filtering": false
        },
        "fit": "average",
        "fn": 60,
        "include_baseline_error": false,
        "n": 60,
        "outlier_excluded": [],
        "reviewed": true,
        "user_excluded": [],
        "value": -0.013397205073852092
    },
    "H2": {
        "error": 0.014682033542845033,
        "error_type": "SEM",
        "filter_outliers_dict": {
            "filter_outliers": true,
            "iterations": 1,
            "std_devs": 3,
            "use_iqr_filtering": false,
            "use_standard_deviation_filtering": false
        },
        "fit": "average",
        "fn": 60,
        "include_baseline_error": false,
        "n": 60,
        "outlier_excluded": [],
        "reviewed": true,
        "user_excluded": [],
        "value": 0.21251002174491684
    },
    "L1": {
        "error": 0.008131370147899507,
        "error_type": "SEM",
        "filter_outliers_dict": {
            "filter_outliers": true,
            "iterations": 1,
            "std_devs": 3,
            "use_iqr_filtering": false,
            "use_standard_deviation_filtering": false
        },
        "fit": "average",
        "fn": 59,
        "include_baseline_error": false,
        "n": 60,
        "outlier_excluded": [
            42
        ],
        "reviewed": true,
        "user_excluded": [],
        "value": -0.029031733187212475
    },
    "L2(CDD)": {
        "error": 0.0,
        "error_type": "SEM",
        "filter_outliers_dict": {
            "filter_outliers": true,
            "iterations": 1,
            "std_devs": 10
        },
        "fit": "average",
        "value": 0.0
    }
}