{
    "AX": {
        "error": 0.01179102990025353,
        "error_type": "SEM",
        "filter_outliers_dict": {
            "filter_outliers": true,
            "iterations": 1,
            "std_devs": 3,
            "use_iqr_filtering": false,
            "use_standard_deviation_filtering": false
        },
        "fit": "average",
        "fn": 35,
        "include_baseline_error": false,
        "modifier_error": 0.0,
        "modifier_value": 0.0,
        "n": 35,
        "outlier_excluded": [],
        "reviewed": true,
        "user_excluded": [],
        "value": 0.020789363135450652
    },
    "CDD": {
        "error": 9.461488599707305e-06,
        "error_type": "SEM",
        "filter_outliers_dict": {
            "filter_outliers": true,
            "iterations": 1,
            "std_devs": 10,
            "use_iqr_filtering": false,
            "use_standard_deviation_filtering": false
        },
        "fit": "average",
        "fn": 35,
        "include_baseline_error": false,
        "modifier_error": 9.594154859029161e-06,
        "modifier_value": 2.077636314567388e-05,
        "n": 35,
        "outlier_excluded": [],
        "reviewed": true,
        "user_excluded": [],
        "value": 4.3299210249512855e-05
    },
    "H1": {
        "error": 0.008246625519340947,
        "error_type": "SEM",
        "filter_outliers_dict": {
            "filter_outliers": true,
            "iterations": 1,
            "std_devs": 3,
            "use_iqr_filtering": false,
            "use_standard_deviation_filtering": false
        },
        "fit": "average",
        "fn": 35,
        "include_baseline_error": false,
        "modifier_error": 0.0,
        "modifier_value": 0.0,
        "n": 35,
        "outlier_excluded": [],
        "reviewed": true,
        "user_excluded": [],
        "value": 0.03033576566085685
    },
    "H2": {
        "error": 0.0073315898944454555,
        "error_type": "SEM",
        "filter_outliers_dict": {
            "filter_outliers": true,
            "iterations": 1,
            "std_devs": 2
        },
        "fit": "average",
        "modifier_error": 0.0,
        "modifier_value": 0.0,
        "value": 0.025026294055630928
    },
    "L1": {
        "error": 0.003347166730877067,
        "error_type": "SEM",
        "filter_outliers_dict": {
            "filter_outliers": true,
            "iterations": 1,
            "std_devs": 3,
            "use_iqr_filtering": false,
            "use_standard_deviation_filtering": false
        },
        "fit": "average",
        "fn": 35,
        "include_baseline_error": false,
        "modifier_error": 0.0,
        "modifier_value": 0.0,
        "n": 35,
        "outlier_excluded": [],
        "reviewed": true,
        "user_excluded": [],
        "value": 0.029717350298804898
    },
    "L2": {
        "error": 0.004619025060950617,
        "error_type": "SEM",
        "filter_outliers_dict": {
            "filter_outliers": true,
            "iterations": 1,
            "std_devs": 3,
            "use_iqr_filtering": false,
            "use_standard_deviation_filtering": false
        },
        "fit": "average",
        "fn": 35,
        "include_baseline_error": false,
        "modifier_error": 0.0,
        "modifier_value": 0.0,
        "n": 35,
        "outlier_excluded": [],
        "reviewed": true,
        "user_excluded": [],
        "value": -0.03870365536256161
    }
}