{
    "Ar36": {
        "error": 0.0008603689269192217,
        "error_type": "SEM",
        "filter_outliers_dict": {
            "filter_outliers": true,
            "iterations": 1,
            "std_devs": 3,
            "use_iqr_filtering": false,
            "use_standard_deviation_filtering": false
        },
        "fit": "linear",
        "fn": 339,
        "include_baseline_error": false,
        "n": 340,
        "outlier_excluded": [
            97
        ],
        "reviewed": true,
        "user_excluded": [],
        "value": 0.311979439731914
    },
    "Ar37": {
        "error": 0.016576065951544608,
        "error_type": "SEM",
        "filter_outliers_dict": {
            "filter_outliers": true,
            "iterations": 1,
            "std_devs": 3,
            "use_iqr_filtering": false,
            "use_standard_deviation_filtering": false
        },
        "fit": "linear",
        "fn": 339,
        "include_baseline_error": false,
        "n": 340,
        "outlier_excluded": [
            96
        ],
        "reviewed": true,
        "user_excluded": [],
        "value": 0.04000991105723744
    },
    "Ar38": {
        "error": 0.0051903887824830235,
        "error_type": "SEM",
        "filter_outliers_dict": {
            "filter_outliers": true,
            "iterations": 1,
            "std_devs": 3,
            "use_iqr_filtering": false,
            "use_standard_deviation_filtering": false
        },
        "fit": "linear",
        "fn": 339,
        "include_baseline_error": false,
        "n": 340,
        "outlier_excluded": [
            229
        ],
        "reviewed": true,
        "user_excluded": [],
        "value": 0.6215506332631349
    },
    "Ar39": {
        "error": 0.009144014529602118,
        "error_type": "SEM",
        "filter_outliers_dict": {
            "filter_outliers": true,
            "iterations": 1,
            "std_devs": 3,
            "use_iqr_filtering": false,
            "use_standard_deviation_filtering": false
        },
        "fit": "linear",
        "fn": 339,
        "include_baseline_error": false,
        "n": 340,
        "outlier_excluded": [
            101
        ],
        "reviewed": true,
        "user_excluded": [],
        "value": 15.309979767405558
    },
    "Ar40": {
        "error": 0.03709500014481114,
        "error_type": "SEM",
        "filter_outliers_dict": {
            "filter_outliers": true,
            "iterations": 1,
            "std_devs": 3,
            "use_iqr_filtering": false,
            "use_standard_deviation_filtering": false
        },
        "fit": "parabolic",
        "fn": 339,
        "include_baseline_error": false,
        "n": 340,
        "outlier_excluded": [
            124
        ],
        "reviewed": true,
        "user_excluded": [],
        "value": 114.65234649265592
    }
}